discordRandomStuff/Noclass.py
discordRandomStuff/__init__.py
discordRandomStuff/welcome.py
DiscordRandomStuff-0.0.1.dist-info/METADATA
DiscordRandomStuff-0.0.1.dist-info/WHEEL
DiscordRandomStuff-0.0.1.dist-info/top_level.txt
DiscordRandomStuff-0.0.1.dist-info/RECORD
