Metadata-Version: 2.1
Name: DiscordRandomStuff
Version: 0.0.1
Summary: It has random thing, it like a start up for you discord bot
Home-page: UNKNOWN
License: MIT
Platform: UNKNOWN
Classifier: Programming Language :: Python :: 3
Classifier: License :: OSI Approved :: MIT License
Classifier: Operating System :: OS Independent
Requires-Python: >=3.6
Requires-Dist: discord.py
Requires-Dist: asyncio
Requires-Dist: discord
